sprockets.mixins.avro_publisher-1.0.0-py3.5-nspkg.pth
sprockets/mixins/avro_publisher/__init__.py
sprockets.mixins.avro_publisher-1.0.0.dist-info/DESCRIPTION.rst
sprockets.mixins.avro_publisher-1.0.0.dist-info/METADATA
sprockets.mixins.avro_publisher-1.0.0.dist-info/RECORD
sprockets.mixins.avro_publisher-1.0.0.dist-info/WHEEL
sprockets.mixins.avro_publisher-1.0.0.dist-info/metadata.json
sprockets.mixins.avro_publisher-1.0.0.dist-info/namespace_packages.txt
sprockets.mixins.avro_publisher-1.0.0.dist-info/top_level.txt
sprockets.mixins.avro_publisher-1.0.0.dist-info/zip-safe
