Metadata-Version: 2.0
Name: sprockets.mixins.avro-publisher
Version: 1.0.0
Summary: Mixin for publishing events to RabbitMQ as avro datums
Home-page: https://github.com/sprockets/sprockets.mixins.avro-publisher
Author: AWeber Communications, Inc.
Author-email: api@aweber.com
License: BSD
Platform: UNKNOWN
Classifier: Development Status :: 3 - Alpha
Classifier: Intended Audience :: Developers
Classifier: License :: OSI Approved :: BSD License
Classifier: Natural Language :: English
Classifier: Operating System :: OS Independent
Classifier: Programming Language :: Python :: 2
Classifier: Programming Language :: Python :: 2.7
Classifier: Programming Language :: Python :: 3
Classifier: Programming Language :: Python :: 3.4
Classifier: Programming Language :: Python :: 3.5
Classifier: Programming Language :: Python :: Implementation :: CPython
Classifier: Programming Language :: Python :: Implementation :: PyPy
Classifier: Topic :: Software Development :: Libraries
Classifier: Topic :: Software Development :: Libraries :: Python Modules
Requires-Dist: avro-python3 (>=1.7.7,<2)
Requires-Dist: sprockets.mixins.amqp (>=1.0.0,<2)
